{
  "_id": {
    "$oid": "634ec0c40bf79f60cfb4d8ec"
  },
  "number": 5,
  "title": "Perfect Square",
  "short_desc": "Given an integer, determine if its a perfect square.",
  "description": "Given an integer *num*, return *true* if *num* **is** a perfect square, and *false* otherwise.\n## Examples\n```isSquare(4) -> true```  \n```isSquare(5) -> false```\n## Constraints\n* 1 <= num <= 100000.",
  "points": 2,
  "function": "isSquare",
  "start_code": "function isSquare(num) {\n\n}",
  "test_print": false,
  "test_cases": [
    { "input": [4], "output": true },
    { "input": [5], "output": false },
    { "input": [1], "output": true },
    { "input": [9], "output": true },
    { "input": [15], "output": false },
    { "input": [36], "output": true },
    { "input": [40], "output": false },
    { "input": [69], "output": false },
    { "input": [81], "output": true },
    { "input": [169], "output": true },
    { "input": [3], "output": false },
    { "input": [98], "output": false },
    { "input": [17161], "output": true },
    { "input": [190], "output": false },
    { "input": [29241], "output": true },
    { "input": [11664], "output": true },
    { "input": [46], "output": false },
    { "input": [26896], "output": true },
    { "input": [9], "output": true },
    { "input": [44], "output": false },
    { "input": [170], "output": false },
    { "input": [60025], "output": true },
    { "input": [231], "output": false },
    { "input": [98], "output": false },
    { "input": [32400], "output": true },
    { "input": [170], "output": false },
    { "input": [184], "output": false },
    { "input": [169], "output": false },
    { "input": [84], "output": false },
    { "input": [28561], "output": true },
    { "input": [484], "output": true },
    { "input": [143], "output": false },
    { "input": [149], "output": false },
    { "input": [13689], "output": true },
    { "input": [154], "output": false },
    { "input": [11881], "output": true },
    { "input": [168], "output": false },
    { "input": [66049], "output": true },
    { "input": [1849], "output": true },
    { "input": [24336], "output": true },
    { "input": [243], "output": false },
    { "input": [110], "output": false },
    { "input": [33489], "output": true },
    { "input": [89], "output": false },
    { "input": [39], "output": false },
    { "input": [310], "output": false },
    { "input": [96721], "output": true },
    { "input": [156], "output": false },
    { "input": [227], "output": false },
    { "input": [84681], "output": true },
    { "input": [17956], "output": true },
    { "input": [57], "output": false },
    { "input": [84100], "output": true },
    { "input": [307], "output": false },
    { "input": [58081], "output": true },
    { "input": [265], "output": false },
    { "input": [17161], "output": true },
    { "input": [164], "output": false },
    { "input": [156], "output": false },
    { "input": [3721], "output": true },
    { "input": [25], "output": false },
    { "input": [48], "output": false },
    { "input": [281], "output": false },
    { "input": [41], "output": false },
    { "input": [204], "output": false },
    { "input": [225], "output": true },
    { "input": [134], "output": false },
    { "input": [89], "output": false },
    { "input": [238], "output": false },
    { "input": [102], "output": false },
    { "input": [113], "output": false },
    { "input": [238], "output": false },
    { "input": [255], "output": false },
    { "input": [299], "output": false },
    { "input": [256], "output": false },
    { "input": [16384], "output": true },
    { "input": [298], "output": false },
    { "input": [19321], "output": true },
    { "input": [291], "output": false },
    { "input": [3721], "output": true },
    { "input": [17161], "output": true },
    { "input": [224], "output": false },
    { "input": [31329], "output": true },
    { "input": [41], "output": false },
    { "input": [90], "output": false },
    { "input": [72], "output": false },
    { "input": [289], "output": false },
    { "input": [41], "output": false },
    { "input": [22201], "output": true },
    { "input": [23104], "output": true },
    { "input": [82944], "output": true },
    { "input": [84], "output": false },
    { "input": [195], "output": false },
    { "input": [237], "output": false },
    { "input": [160], "output": false },
    { "input": [237], "output": false },
    { "input": [316], "output": false },
    { "input": [258], "output": false },
    { "input": [5041], "output": true },
    { "input": [79524], "output": true }
  ]
}
